hagis.py
hagis-0.8.7.dist-info/METADATA
hagis-0.8.7.dist-info/WHEEL
hagis-0.8.7.dist-info/top_level.txt
hagis-0.8.7.dist-info/RECORD
