Metadata-Version: 2.1
Name: hagis
Version: 0.8.7
Summary: A high availability GIS client
Author-email: Jiro Shirota <jshirota@gmail.com>
Project-URL: Homepage, https://github.com/jshirota/Hagis
Project-URL: Bug Tracker, https://github.com/jshirota/Hagis/issues
Classifier: Programming Language :: Python :: 3
Classifier: License :: OSI Approved :: MIT License
Classifier: Operating System :: OS Independent
Requires-Python: >=3.7
